tri-buf.v
module tri_buf(
    input [15:0] a,
    output [15:0] bus,
    input enable
);

    assign bus = enable ? a : 16'bz;

endmodule

my_reg.v
module my_reg (clk, bus, enable, data_out);

input clk;
input [15:0] bus;  // en=1 bus value is stored in reg, en=0
input enable;  // en=0 reg value is unchanged
output reg [15:0] data_out;  // output from reg

always @(posedge clk) begin
    if (enable) begin  // en=1
        data_out <= bus;
    end
end

endmodule

my_alu.v
module my_alu (a_in,bus,addsub,g_out);
    input [15:0] a_in;
    input [15:0] bus;
    input addsub;
    output reg [15:0] g_out;

    always @(*) begin
        if (addsub==1'b0) begin
            g_out = a_in + bus;
        end 
        else begin
            g_out = a_in - bus;
        end
    end
endmodule

my_fsm.v
module my_fsm (
    input rst,
    input clk,
    input [4:0] instruction,
    input [1:0] src_sel,
    output reg [2:0] reg_en, //change number of bits depending on how many registers you have
    output reg [2:0] reg_tri, //change this too
    output reg a_en,
    output reg a_tri,
    output reg g_en,
    output reg g_tri,
    output reg addsub
);

    always @(*) begin
        reg_tri = 3'b000; // Tri-state register 0 to bus
        reg_en = 3'b000; // Enable register 0 to store value from bus
        a_en = 0;
        a_tri = 0;
        g_en = 0;
        g_tri = 0;
        addsub = 0; // Default to addition

        case (instruction)
            5'b00000: begin // load
                reg_en[0] = 1; // Enable register 0 to store value from bus
            end 

            5'b00001: begin // move
                reg_tri [0] = 1; // Tri-state register 0 to bus
                reg_en [1] = 1; // Enable register 1 to store value from bus
            end

            5'b00010: begin //add
                addsub = 1'b0; // Set addsub to 0 for addition
                g_en = 1'b1; // Enable register G to store result from ALU
                g_tri = 1'b1; // Tri-state register G to bus
                reg_en[0] = 1'b1;; // Enable register 0 to store value from bus
            end

            5'b00011: begin //subtract
                addsub = 1'b1; // Set addsub to 1 for subtraction
                g_en = 1'b1; // Enable register G to store result from ALU
                g_tri = 1'b1; // Tri-state register G to bus
                reg_en [0] = 2'b01; // Enable register 0 to store value from bus
            end

            default: begin
                reg_tri = 2'b00; // Tri-state register 0 to bus
                reg_en = 2'b00; // Enable register 0 to store value from bus
                a_en = 0;
                a_tri = 0;
                g_en = 0;
                g_tri = 0;
                addsub = 0; // Default to addition
            end
        endcase
    end
    
endmodule

top.v
module top (
    input clk,
    input rst,
    input [4:0] instruction,
    input [15:0] data_in, 
    output [15:0] bus_out 
);

    wire [15:0] bus;          
    wire [15:0] alu_result;  
    assign bus_out = bus; 

    wire [2:0] reg_en, reg_tri; 
    wire a_en, g_en, g_tri, addsub;

    wire [15:0] r0_out, r1_out, r2_out, a_reg_out, g_reg_out;


    my_fsm controller (
        .rst(rst),
        .clk(clk),
        .instruction(instruction),
        .reg_en(reg_en),
        .reg_tri(reg_tri),
        .a_en(a_en),
        .g_en(g_en),
        .g_tri(g_tri),
        .addsub(addsub)
    );


    my_reg R0 (.clk(clk), .bus(bus), .enable(reg_en[0]), .data_out(r0_out));
    my_reg R1 (.clk(clk), .bus(bus), .enable(reg_en[1]), .data_out(r1_out));
    my_reg R2 (.clk(clk), .bus(bus), .enable(reg_en[2]), .data_out(r2_out));


    my_reg A_REG (.clk(clk), .bus(bus), .enable(a_en), .data_out(a_reg_out));
    my_alu alu_inst (
        .a_in(a_reg_out), 
        .bus(bus), 
        .addsub(addsub), 
        .g_out(alu_result)
    );

    my_reg G_REG (.clk(clk), .bus(alu_result), .enable(g_en), .data_out(g_reg_out));


    tri_buf tri_r0 (.a(r0_out), .bus(bus), .enable(reg_tri[0]));
    tri_buf tri_r1 (.a(r1_out), .bus(bus), .enable(reg_tri[1]));
    tri_buf tri_r2 (.a(r2_out), .bus(bus), .enable(reg_tri[2]));

    tri_buf tri_g  (.a(g_reg_out), .bus(bus), .enable(g_tri));

    wire ldi_enable = (instruction == 5'b00000);
    tri_buf tri_ext (.a(data_in), .bus(bus), .enable(ldi_enable));

endmodule

essentials_tb.v
`timescale 1ns / 1ps


module essentials_tb;
    reg clk;
    reg reset;
    reg [4:0] instruction_5bit; // This is what the FSM actually uses 
    reg [15:0] data_in;     

    // Corrected to 3 bits to match the updated FSM
    wire [2:0] reg_en, reg_tri; 
    wire a_en, a_tri, g_en, g_tri;
    wire addsub;

    initial clk = 0;
    always  #10 clk = ~clk;

    wire [15:0] bus_monitor;

    // Instantiate the FSM (or the TOP module if you moved to the full architecture)
    my_fsm fsm (
        .rst(reset),
        .clk(clk),
        .instruction(instruction_5bit),
        .src_sel(data_in[1:0]),
        .reg_en(reg_en),
        .reg_tri(reg_tri),
        .a_en(a_en),
        .a_tri(a_tri),
        .g_en(g_en),
        .g_tri(g_tri),
        .addsub(addsub)
    );

    top top (
        .clk(clk),
        .rst(reset),
        .instruction(instruction_5bit),
        .data_in(data_in),
        .bus_out(bus_monitor) // bus_monitor now connects directly to the system bus
    );

    task apply_instr;
        input [4:0] opcode;   // Expanded to handle 5-bit total instruction
        input [1:0] dest;
        input [15:0] imm_src;
        input [63:0] label;
        begin
            @(negedge clk);       
            // Now correctly updates the 5-bit instruction used by the FSM
            instruction_5bit = {opcode[4:0]}; // Only opcode is used for FSM control
            data_in = imm_src;
            @(posedge clk); #1;   
            @(posedge clk); #1;
            $display("[%0t ns] %s | Instr: %b | Data_In: 0x%h | Bus: 0x%h | AddSub: %b",
                     $time, label, instruction_5bit, data_in, bus_monitor, addsub);
        end
    endtask
    
    initial begin
        reset       = 1;
        instruction_5bit = 5'b00000;
        data_in     = 16'h0000;

        @(posedge clk); #1;
        @(posedge clk); #1;
        reset = 0;
        $display("=== Reset released at %0t ns ===", $time);

        // TEST 1 – LDI R0, 0x000A   (R0 = 10)
        $display("\n--- LDI tests ---");
        apply_instr(5'b00000, 2'b00, 16'h000A, "LDI_R0 ");

        // TEST 2 – LDI R1, 0x0005   (R1 = 5)
        apply_instr(5'b00000, 2'b01, 16'h0005, "LDI_R1 ");

        // TEST 3 – LDI R2, 0x0003   (R2 = 3)
        apply_instr(5'b00000, 2'b10, 16'h0003, "LDI_R2 ");

        // TEST 4 – MOV R2, R0 (R2 = R0 = 10) - data_in[1:0] encodes the source register index (R0 = 0)
        $display("\n--- MOV test ---");
        apply_instr(5'b00001, 2'b10, 16'h0000, "MOV_R2 ");

        // TEST 5 – ADD R0, R1       (R0 = R0 + R1 = 10 + 5 = 15)
        $display("\n--- ADD test ---");
        apply_instr(5'b00010, 2'b00, 16'h0001, "ADD_R0 ");

        // TEST 6 – SUB R0, R2       (R0 = R0 - R2 = 15 - 10 = 5)
        $display("\n--- SUB test ---");
        apply_instr(5'b00011, 2'b00, 16'h0002, "SUB_R0 ");

        // TEST 7 – ADD R1, R2       (R1 = R1 + R2 = 5 + 10 = 15)
        apply_instr(5'b00010, 2'b01, 16'h0002, "ADD_R1 ");

        // TEST 8 – SUB R2, R1       (R2 = R2 - R1 = 10 - 15 = -5)
        apply_instr(5'b00011, 2'b10, 16'h0001, "SUB_R2 ");

        // TEST 9 – LDI R0, 0x0000   (R0 = 0, boundary / zero test)
        $display("\n--- Edge-case tests ---");
        apply_instr(5'b00000, 2'b00, 16'h0000, "LDI_R0Z");

        // TEST 10 – ADD R0, R1      (0 + 15 = 15, add-to-zero)
        apply_instr(5'b00010, 2'b00, 16'h0001, "ADD_0+R1");

        // TEST 11 – SUB R0, R0      (R0 - R0 = 0, self-subtract)
        apply_instr(5'b00011, 2'b00, 16'h0000, "SUB_R0R0");

        repeat(4) @(posedge clk);
        $display("\n=== Simulation complete at %0t ns ===", $time);
        $finish;
    end

    initial begin
        $dumpfile("essentials_tb.vcd");
        $dumpvars(0, essentials_tb);
    end

endmodule

essentials_tb.vcd
$date
	Thu May 14 13:21:57 2026
$end
$version
	Icarus Verilog
$end
$timescale
	1ps
$end
$scope module essentials_tb $end
$var wire 3 ! reg_tri [2:0] $end
$var wire 3 " reg_en [2:0] $end
$var wire 1 # g_tri $end
$var wire 1 $ g_en $end
$var wire 16 % bus_monitor [15:0] $end
$var wire 1 & addsub $end
$var wire 1 ' a_tri $end
$var wire 1 ( a_en $end
$var reg 1 ) clk $end
$var reg 16 * data_in [15:0] $end
$var reg 5 + instruction_5bit [4:0] $end
$var reg 1 , reset $end
$scope module fsm $end
$var wire 1 ) clk $end
$var wire 5 - instruction [4:0] $end
$var wire 1 , rst $end
$var wire 2 . src_sel [1:0] $end
$var reg 1 ( a_en $end
$var reg 1 ' a_tri $end
$var reg 1 & addsub $end
$var reg 1 $ g_en $end
$var reg 1 # g_tri $end
$var reg 3 / reg_en [2:0] $end
$var reg 3 0 reg_tri [2:0] $end
$upscope $end
$scope module top $end
$var wire 16 1 bus [15:0] $end
$var wire 16 2 bus_out [15:0] $end
$var wire 1 ) clk $end
$var wire 16 3 data_in [15:0] $end
$var wire 5 4 instruction [4:0] $end
$var wire 1 , rst $end
$var wire 3 5 reg_tri [2:0] $end
$var wire 3 6 reg_en [2:0] $end
$var wire 16 7 r2_out [15:0] $end
$var wire 16 8 r1_out [15:0] $end
$var wire 16 9 r0_out [15:0] $end
$var wire 1 : ldi_enable $end
$var wire 1 ; g_tri $end
$var wire 16 < g_reg_out [15:0] $end
$var wire 1 = g_en $end
$var wire 16 > alu_result [15:0] $end
$var wire 1 ? addsub $end
$var wire 16 @ a_reg_out [15:0] $end
$var wire 1 A a_en $end
$scope module A_REG $end
$var wire 16 B bus [15:0] $end
$var wire 1 ) clk $end
$var wire 1 A enable $end
$var reg 16 C data_out [15:0] $end
$upscope $end
$scope module G_REG $end
$var wire 1 ) clk $end
$var wire 1 = enable $end
$var wire 16 D bus [15:0] $end
$var reg 16 E data_out [15:0] $end
$upscope $end
$scope module R0 $end
$var wire 16 F bus [15:0] $end
$var wire 1 ) clk $end
$var wire 1 G enable $end
$var reg 16 H data_out [15:0] $end
$upscope $end
$scope module R1 $end
$var wire 16 I bus [15:0] $end
$var wire 1 ) clk $end
$var wire 1 J enable $end
$var reg 16 K data_out [15:0] $end
$upscope $end
$scope module R2 $end
$var wire 16 L bus [15:0] $end
$var wire 1 ) clk $end
$var wire 1 M enable $end
$var reg 16 N data_out [15:0] $end
$upscope $end
$scope module alu_inst $end
$var wire 16 O a_in [15:0] $end
$var wire 16 P bus [15:0] $end
$var wire 1 ? addsub $end
$var reg 16 Q g_out [15:0] $end
$upscope $end
$scope module controller $end
$var wire 1 ) clk $end
$var wire 5 R instruction [4:0] $end
$var wire 1 , rst $end
$var wire 2 S src_sel [1:0] $end
$var reg 1 A a_en $end
$var reg 1 T a_tri $end
$var reg 1 ? addsub $end
$var reg 1 = g_en $end
$var reg 1 ; g_tri $end
$var reg 3 U reg_en [2:0] $end
$var reg 3 V reg_tri [2:0] $end
$upscope $end
$scope module tri_ext $end
$var wire 16 W a [15:0] $end
$var wire 16 X bus [15:0] $end
$var wire 1 : enable $end
$upscope $end
$scope module tri_g $end
$var wire 16 Y a [15:0] $end
$var wire 16 Z bus [15:0] $end
$var wire 1 ; enable $end
$upscope $end
$scope module tri_r0 $end
$var wire 16 [ a [15:0] $end
$var wire 16 \ bus [15:0] $end
$var wire 1 ] enable $end
$upscope $end
$scope module tri_r1 $end
$var wire 16 ^ a [15:0] $end
$var wire 16 _ bus [15:0] $end
$var wire 1 ` enable $end
$upscope $end
$scope module tri_r2 $end
$var wire 16 a a [15:0] $end
$var wire 16 b bus [15:0] $end
$var wire 1 c enable $end
$upscope $end
$upscope $end
$scope task apply_instr $end
$var reg 2 d dest [1:0] $end
$var reg 16 e imm_src [15:0] $end
$var reg 64 f label [63:0] $end
$var reg 5 g opcode [4:0] $end
$upscope $end
$upscope $end
$enddefinitions $end
$comment Show the parameter values. $end
$dumpall
$end
#0
$dumpvars
bx g
bx f
bx e
bx d
0c
b0 b
bx a
0`
b0 _
bx ^
0]
b0 \
bx [
b0 Z
bx Y
b0 X
b0 W
b0 V
b1 U
0T
bz S
b0 R
bx Q
b0 P
bx O
bx N
0M
b0 L
bx K
0J
b0 I
bx H
1G
b0 F
bx E
bx D
bx C
b0 B
0A
bx @
0?
bx >
0=
bx <
0;
1:
bx 9
bx 8
bx 7
b1 6
b0 5
b0 4
b0 3
b0 2
b0 1
b0 0
b1 /
b0 .
b0 -
1,
b0 +
b0 *
0)
0(
0'
0&
b0 %
0$
0#
b1 "
b0 !
$end
#10000
b0 9
b0 H
b0 [
1)
#20000
0)
#30000
1)
#31000
b1001100010001000100100101011111010100100011000000100000 f
b1010 e
b0 d
b0 g
0,
#40000
b10 .
b1010 %
b1010 2
b1010 1
b1010 B
b1010 F
b1010 I
b1010 L
b1010 P
b1010 X
b1010 Z
b1010 \
b1010 _
b1010 b
b1010 *
b1010 3
b1010 W
0)
#50000
b1010 9
b1010 H
b1010 [
1)
#60000
0)
#70000
1)
#71000
b1001100010001000100100101011111010100100011000100100000 f
b101 e
b1 d
#80000
b1 .
b101 %
b101 2
b101 1
b101 B
b101 F
b101 I
b101 L
b101 P
b101 X
b101 Z
b101 \
b101 _
b101 b
b101 *
b101 3
b101 W
0)
#90000
b101 9
b101 H
b101 [
1)
#100000
0)
#110000
1)
#111000
b1001100010001000100100101011111010100100011001000100000 f
b11 e
b10 d
#120000
b11 .
b11 %
b11 2
b11 1
b11 B
b11 F
b11 I
b11 L
b11 P
b11 X
b11 Z
b11 \
b11 _
b11 b
b11 *
b11 3
b11 W
0)
#130000
b11 9
b11 H
b11 [
1)
#140000
0)
#150000
1)
#151000
b1001101010011110101011001011111010100100011001000100000 f
b0 e
b1 g
#160000
1J
1]
0G
b0 .
b1 !
b1 0
b10 "
b10 /
b1 5
b1 V
b10 6
b10 U
b11 %
b11 2
b11 1
b11 B
b11 F
b11 I
b11 L
b11 P
b11 X
b11 Z
b11 \
b11 _
b11 b
b0 *
b0 3
b0 W
0:
b1 +
b1 -
b1 4
b1 R
0)
#170000
b11 8
b11 K
b11 ^
1)
#180000
0)
#190000
1)
#191000
b1000001010001000100010001011111010100100011000000100000 f
b1 e
b0 d
b10 g
#200000
1G
bx %
bx 2
bx 1
bx B
bx F
bx I
bx L
bx P
bx X
bx Z
bx \
bx _
bx b
0J
0]
b1 .
1;
1=
b1 6
b1 U
b0 5
b0 V
1#
1$
b1 "
b1 /
b0 !
b0 0
b1 *
b1 3
b1 W
b10 +
b10 -
b10 4
b10 R
0)
#210000
bx 9
bx H
bx [
1)
#220000
0)
#230000
1)
#231000
b1010011010101010100001001011111010100100011000000100000 f
b10 e
b11 g
#240000
b10 .
1&
1#
1$
b1 "
b1 /
1?
1;
1=
b1 6
b1 U
b10 *
b10 3
b10 W
b11 +
b11 -
b11 4
b11 R
0)
#250000
1)
#260000
0)
#270000
1)
#271000
b1000001010001000100010001011111010100100011000100100000 f
b1 d
b10 g
#280000
0?
1;
1=
b1 6
b1 U
0&
1#
1$
b1 "
b1 /
b10 +
b10 -
b10 4
b10 R
0)
#290000
1)
#300000
0)
#310000
1)
#311000
b1010011010101010100001001011111010100100011001000100000 f
b1 e
b10 d
b11 g
#320000
b1 .
1&
1#
1$
b1 "
b1 /
1?
1;
1=
b1 6
b1 U
b1 *
b1 3
b1 W
b11 +
b11 -
b11 4
b11 R
0)
#330000
1)
#340000
0)
#350000
1)
#351000
b1001100010001000100100101011111010100100011000001011010 f
b0 e
b0 d
b0 g
#360000
b0 %
b0 2
b0 1
b0 B
b0 F
b0 I
b0 L
b0 P
b0 X
b0 Z
b0 \
b0 _
b0 b
b0 .
0?
0;
0=
b1 6
b1 U
0&
0#
0$
b1 "
b1 /
b0 *
b0 3
b0 W
1:
b0 +
b0 -
b0 4
b0 R
0)
#370000
b0 9
b0 H
b0 [
1)
#380000
0)
#390000
1)
#391000
b100000101000100010001000101111100110000001010110101001000110001 f
b1 e
b10 g
#400000
b1 .
1#
1$
b1 "
b1 /
1;
1=
b1 6
b1 U
bx %
bx 2
bx 1
bx B
bx F
bx I
bx L
bx P
bx X
bx Z
bx \
bx _
bx b
b1 *
b1 3
b1 W
0:
b10 +
b10 -
b10 4
b10 R
0)
#410000
bx 9
bx H
bx [
1)
#420000
0)
#430000
1)
#431000
b101001101010101010000100101111101010010001100000101001000110000 f
b0 e
b11 g
#440000
b0 .
1?
1;
1=
b1 6
b1 U
1&
1#
1$
b1 "
b1 /
b0 *
b0 3
b0 W
b11 +
b11 -
b11 4
b11 R
0)
