tri-buf.v
module tri_buf(
    input [15:0] a,
    output [15:0] bus,
    input enable
);

    assign bus = enable ? a : 16'bz;

endmodule

my_reg.v
module my_reg (clk, bus, enable, data_out);

input clk;
input [15:0] bus;  // en=1 bus value is stored in reg, en=0
input enable;  // en=0 reg value is unchanged
output reg [15:0] data_out;  // output from reg

always @(posedge clk) begin
    if (enable) begin  // en=1
        data_out <= bus;
    end
end

endmodule

my_alu.v
module my_alu (a_in,bus,addsub,g_out);
    input [15:0] a_in;
    input [15:0] bus;
    input addsub;
    output reg [15:0] g_out;

    always @(*) begin
        if (addsub==1'b0) begin
            g_out = a_in + bus;
        end 
        else begin
            g_out = a_in - bus;
        end
    end
endmodule

my_fsm.v
module my_fsm (
    input rst,
    input clk,
    input [4:0] instruction, 
    input [1:0] src_sel,   
    output reg [2:0] reg_en,
    output reg [2:0] reg_tri,
    output reg a_en,
    output reg a_tri,
    output reg g_en,
    output reg g_tri,
    output reg addsub
);

    wire [2:0] opcode = instruction[2:0];
    wire [1:0] dest   = instruction[4:3];

    // 3-phase sequencer for ADD/SUB:
    //   phase 0 → dest reg → A_REG
    //   phase 1 → src reg  → G_REG (ALU computes, no bus conflict)
    //   phase 2 → G_REG    → dest reg
    reg [1:0] phase;

    always @(posedge clk or posedge rst) begin
        if (rst)
            phase <= 2'd0;
        else begin
            if (opcode == 3'b010 || opcode == 3'b011)
                phase <= (phase == 2'd2) ? 2'd0 : phase + 1;
            else
                phase <= 2'd0;
        end
    end

    always @(*) begin
        reg_tri = 3'b000;
        reg_en  = 3'b000;
        a_en    = 1'b0;
        a_tri   = 1'b0;
        g_en    = 1'b0;
        g_tri   = 1'b0;
        addsub  = 1'b0;

        case (opcode)

            // LDI: data_in drives bus via tri_ext in top.v; dest from instruction[4:3]
            3'b000: begin
                reg_en = (3'b001 << dest);
            end

            // MOV: src (src_sel) → bus → dest (instruction[4:3])
            3'b001: begin
                reg_tri = (3'b001 << src_sel);
                reg_en  = (3'b001 << dest);
            end

            // ADD / SUB – three-phase, no bus contention
            3'b010,
            3'b011: begin
                addsub = opcode[0];  // 0 for ADD, 1 for SUB

                case (phase)
                    2'd0: begin
                        // dest reg → bus → A_REG (load first operand)
                        reg_tri = (3'b001 << dest);
                        a_en    = 1'b1;
                    end
                    2'd1: begin
                        // src reg → bus → ALU → G_REG (no g_tri: no bus conflict)
                        reg_tri = (3'b001 << src_sel);
                        g_en    = 1'b1;
                    end
                    2'd2: begin
                        // G_REG → bus → dest reg (write result)
                        g_tri  = 1'b1;
                        reg_en = (3'b001 << dest);
                    end
                    default: begin end
                endcase
            end

            default: begin end
        endcase
    end

endmodule

top.v
module top (
    input clk,
    input rst,
    input [4:0] instruction,
    input [15:0] data_in,
    output [15:0] bus_out
);

    wire [15:0] bus;
    wire [15:0] alu_result;
    assign bus_out = bus;

    wire [2:0] reg_en, reg_tri;
    wire a_en, a_tri, g_en, g_tri, addsub;

    wire [15:0] r0_out, r1_out, r2_out, a_reg_out, g_reg_out;

    my_fsm controller (
        .rst(rst),
        .clk(clk),
        .instruction(instruction),
        .src_sel(data_in[1:0]),
        .reg_en(reg_en),
        .reg_tri(reg_tri),
        .a_en(a_en),
        .a_tri(a_tri),
        .g_en(g_en),
        .g_tri(g_tri),
        .addsub(addsub)
    );

    my_reg R0 (.clk(clk), .bus(bus), .enable(reg_en[0]), .data_out(r0_out));
    my_reg R1 (.clk(clk), .bus(bus), .enable(reg_en[1]), .data_out(r1_out));
    my_reg R2 (.clk(clk), .bus(bus), .enable(reg_en[2]), .data_out(r2_out));

    my_reg A_REG (.clk(clk), .bus(bus), .enable(a_en), .data_out(a_reg_out));
    my_alu alu_inst (
        .a_in(a_reg_out),
        .bus(bus),
        .addsub(addsub),
        .g_out(alu_result)
    );

    my_reg G_REG (.clk(clk), .bus(alu_result), .enable(g_en), .data_out(g_reg_out));

    tri_buf tri_r0 (.a(r0_out), .bus(bus), .enable(reg_tri[0]));
    tri_buf tri_r1 (.a(r1_out), .bus(bus), .enable(reg_tri[1]));
    tri_buf tri_r2 (.a(r2_out), .bus(bus), .enable(reg_tri[2]));
    tri_buf tri_g  (.a(g_reg_out), .bus(bus), .enable(g_tri));

    // LDI: data_in drives the bus when opcode bits [2:0] == LDI
    wire ldi_enable = (instruction[2:0] == 3'b000);
    tri_buf tri_ext (.a(data_in), .bus(bus), .enable(ldi_enable));

endmodule

essentials_tb.v
`timescale 1ns / 1ps


module essentials_tb;
    reg clk;
    reg reset;
    reg [4:0] instruction_5bit; 
    reg [15:0] data_in;     

    // Corrected to 3 bits to match the updated FSM
    wire [2:0] reg_en, reg_tri; 
    wire a_en, a_tri, g_en, g_tri;
    wire addsub;

    initial clk = 0;
    always  #10 clk = ~clk;

    wire [15:0] bus_monitor;

    my_fsm fsm (
        .rst(reset),
        .clk(clk),
        .instruction(instruction_5bit),
        .src_sel(data_in[1:0]),
        .reg_en(reg_en),
        .reg_tri(reg_tri),
        .a_en(a_en),
        .a_tri(a_tri),
        .g_en(g_en),
        .g_tri(g_tri),
        .addsub(addsub)
    );

    top top (
        .clk(clk),
        .rst(reset),
        .instruction(instruction_5bit),
        .data_in(data_in),
        .bus_out(bus_monitor) 
    );

    task apply_instr;
        input [4:0] opcode;   
        input [1:0] dest;    
        input [15:0] imm_src;
        input [63:0] label;
        begin
            @(negedge clk);

            instruction_5bit = {dest, opcode[2:0]};
            data_in = imm_src;
            @(posedge clk); #1;
            @(posedge clk); #1;

            if (opcode[2:0] == 3'b010 || opcode[2:0] == 3'b011) begin
                @(posedge clk); #1;
            end
            $display("[%0t ns] %s | Instr: %b | Data_In: 0x%d | Bus: 0x%d | AddSub: %d",
                     $time, label, instruction_5bit, data_in, bus_monitor, addsub);
        end
    endtask
    
    initial begin
        reset       = 1;
        instruction_5bit = 5'b00000;
        data_in     = 16'h0000;

        @(posedge clk); #1;
        @(posedge clk); #1;
        reset = 0;
        $display("=== Reset released at %0t ns ===", $time);

        // TEST 1 – LDI R0, 0x000A   (R0 = 10)
        $display("\n--- LDI tests ---");
        apply_instr(5'b00000, 2'b00, 16'h000A, "LDI_R0 ");

        // TEST 2 – LDI R1, 0x0005   (R1 = 5)
        apply_instr(5'b00000, 2'b01, 16'h0005, "LDI_R1 ");

        // TEST 3 – LDI R2, 0x0003   (R2 = 3)
        apply_instr(5'b00000, 2'b10, 16'h0003, "LDI_R2 ");

        // TEST 4 – MOV R2, R0 (R2 = R0 = 10) - data_in[1:0] encodes the source register index (R0 = 0)
        $display("\n--- MOV test ---");
        apply_instr(5'b00001, 2'b10, 16'h0000, "MOV_R2 ");

        // TEST 5 – ADD R0, R1       (R0 = R0 + R1 = 10 + 5 = 15)
        $display("\n--- ADD test ---");
        apply_instr(5'b00010, 2'b00, 16'h0001, "ADD_R0 ");

        // TEST 6 – SUB R0, R2       (R0 = R0 - R2 = 15 - 10 = 5)
        $display("\n--- SUB test ---");
        apply_instr(5'b00011, 2'b00, 16'h0002, "SUB_R0 ");

        // TEST 7 – ADD R1, R2       (R1 = R1 + R2 = 5 + 10 = 15)
        apply_instr(5'b00010, 2'b01, 16'h0002, "ADD_R1 ");

        // TEST 8 – SUB R2, R1       (R2 = R2 - R1 = 10 - 15 = -5)
        apply_instr(5'b00011, 2'b10, 16'h0001, "SUB_R2 ");

        // TEST 9 – LDI R0, 0x0000   (R0 = 0, boundary / zero test)
        $display("\n--- Edge-case tests ---");
        apply_instr(5'b00000, 2'b00, 16'h0000, "LDI_R0Z");

        // TEST 10 – ADD R0, R1      (0 + 15 = 15, add-to-zero)
        apply_instr(5'b00010, 2'b00, 16'h0001, "ADD_0+R1");

        // TEST 11 – SUB R0, R0      (R0 - R0 = 0, self-subtract)
        apply_instr(5'b00011, 2'b00, 16'h0000, "SUB_R0R0");

        repeat(4) @(posedge clk);
        $display("\n=== Simulation complete at %0t ns ===", $time);
        $finish;
    end

    initial begin
        $dumpfile("essentials_tb.vcd");
        $dumpvars(0, essentials_tb);
    end

endmodule

essentials_tb.vcd
$date
	Thu May 14 13:49:22 2026
$end
$version
	Icarus Verilog
$end
$timescale
	1ps
$end
$scope module essentials_tb $end
$var wire 3 ! reg_tri [2:0] $end
$var wire 3 " reg_en [2:0] $end
$var wire 1 # g_tri $end
$var wire 1 $ g_en $end
$var wire 16 % bus_monitor [15:0] $end
$var wire 1 & addsub $end
$var wire 1 ' a_tri $end
$var wire 1 ( a_en $end
$var reg 1 ) clk $end
$var reg 16 * data_in [15:0] $end
$var reg 5 + instruction_5bit [4:0] $end
$var reg 1 , reset $end
$scope module fsm $end
$var wire 1 ) clk $end
$var wire 5 - instruction [4:0] $end
$var wire 1 , rst $end
$var wire 2 . src_sel [1:0] $end
$var wire 3 / opcode [2:0] $end
$var wire 2 0 dest [1:0] $end
$var reg 1 ( a_en $end
$var reg 1 ' a_tri $end
$var reg 1 & addsub $end
$var reg 1 $ g_en $end
$var reg 1 # g_tri $end
$var reg 2 1 phase [1:0] $end
$var reg 3 2 reg_en [2:0] $end
$var reg 3 3 reg_tri [2:0] $end
$upscope $end
$scope module top $end
$var wire 16 4 bus [15:0] $end
$var wire 16 5 bus_out [15:0] $end
$var wire 1 ) clk $end
$var wire 16 6 data_in [15:0] $end
$var wire 5 7 instruction [4:0] $end
$var wire 1 , rst $end
$var wire 3 8 reg_tri [2:0] $end
$var wire 3 9 reg_en [2:0] $end
$var wire 16 : r2_out [15:0] $end
$var wire 16 ; r1_out [15:0] $end
$var wire 16 < r0_out [15:0] $end
$var wire 1 = ldi_enable $end
$var wire 1 > g_tri $end
$var wire 16 ? g_reg_out [15:0] $end
$var wire 1 @ g_en $end
$var wire 16 A alu_result [15:0] $end
$var wire 1 B addsub $end
$var wire 1 C a_tri $end
$var wire 16 D a_reg_out [15:0] $end
$var wire 1 E a_en $end
$scope module A_REG $end
$var wire 16 F bus [15:0] $end
$var wire 1 ) clk $end
$var wire 1 E enable $end
$var reg 16 G data_out [15:0] $end
$upscope $end
$scope module G_REG $end
$var wire 1 ) clk $end
$var wire 1 @ enable $end
$var wire 16 H bus [15:0] $end
$var reg 16 I data_out [15:0] $end
$upscope $end
$scope module R0 $end
$var wire 16 J bus [15:0] $end
$var wire 1 ) clk $end
$var wire 1 K enable $end
$var reg 16 L data_out [15:0] $end
$upscope $end
$scope module R1 $end
$var wire 16 M bus [15:0] $end
$var wire 1 ) clk $end
$var wire 1 N enable $end
$var reg 16 O data_out [15:0] $end
$upscope $end
$scope module R2 $end
$var wire 16 P bus [15:0] $end
$var wire 1 ) clk $end
$var wire 1 Q enable $end
$var reg 16 R data_out [15:0] $end
$upscope $end
$scope module alu_inst $end
$var wire 16 S a_in [15:0] $end
$var wire 16 T bus [15:0] $end
$var wire 1 B addsub $end
$var reg 16 U g_out [15:0] $end
$upscope $end
$scope module controller $end
$var wire 1 ) clk $end
$var wire 5 V instruction [4:0] $end
$var wire 1 , rst $end
$var wire 2 W src_sel [1:0] $end
$var wire 3 X opcode [2:0] $end
$var wire 2 Y dest [1:0] $end
$var reg 1 E a_en $end
$var reg 1 C a_tri $end
$var reg 1 B addsub $end
$var reg 1 @ g_en $end
$var reg 1 > g_tri $end
$var reg 2 Z phase [1:0] $end
$var reg 3 [ reg_en [2:0] $end
$var reg 3 \ reg_tri [2:0] $end
$upscope $end
$scope module tri_ext $end
$var wire 16 ] a [15:0] $end
$var wire 16 ^ bus [15:0] $end
$var wire 1 = enable $end
$upscope $end
$scope module tri_g $end
$var wire 16 _ a [15:0] $end
$var wire 16 ` bus [15:0] $end
$var wire 1 > enable $end
$upscope $end
$scope module tri_r0 $end
$var wire 16 a a [15:0] $end
$var wire 16 b bus [15:0] $end
$var wire 1 c enable $end
$upscope $end
$scope module tri_r1 $end
$var wire 16 d a [15:0] $end
$var wire 16 e bus [15:0] $end
$var wire 1 f enable $end
$upscope $end
$scope module tri_r2 $end
$var wire 16 g a [15:0] $end
$var wire 16 h bus [15:0] $end
$var wire 1 i enable $end
$upscope $end
$upscope $end
$scope task apply_instr $end
$var reg 2 j dest [1:0] $end
$var reg 16 k imm_src [15:0] $end
$var reg 64 l label [63:0] $end
$var reg 5 m opcode [4:0] $end
$upscope $end
$upscope $end
$enddefinitions $end
$comment Show the parameter values. $end
$dumpall
$end
#0
$dumpvars
bx m
bx l
bx k
bx j
0i
b0 h
bx g
0f
b0 e
bx d
0c
b0 b
bx a
b0 `
bx _
b0 ^
b0 ]
b0 \
b1 [
b0 Z
b0 Y
b0 X
b0 W
b0 V
bx U
b0 T
bx S
bx R
0Q
b0 P
bx O
0N
b0 M
bx L
1K
b0 J
bx I
bx H
bx G
b0 F
0E
bx D
0C
0B
bx A
0@
bx ?
0>
1=
bx <
bx ;
bx :
b1 9
b0 8
b0 7
b0 6
b0 5
b0 4
b0 3
b1 2
b0 1
b0 0
b0 /
b0 .
b0 -
1,
b0 +
b0 *
0)
0(
0'
0&
b0 %
0$
0#
b1 "
b0 !
$end
#10000
b0 <
b0 L
b0 a
1)
#20000
0)
#30000
1)
#31000
b1001100010001000100100101011111010100100011000000100000 l
b1010 k
b0 j
b0 m
0,
#40000
b1 "
b1 2
b1 9
b1 [
b10 .
b10 W
b1010 %
b1010 5
b1010 4
b1010 F
b1010 J
b1010 M
b1010 P
b1010 T
b1010 ^
b1010 `
b1010 b
b1010 e
b1010 h
b1010 *
b1010 6
b1010 ]
0)
#50000
b1010 <
b1010 L
b1010 a
1)
#60000
0)
#70000
1)
#71000
b1001100010001000100100101011111010100100011000100100000 l
b101 k
b1 j
#80000
1N
0K
b10 "
b10 2
b10 9
b10 [
b1 .
b1 W
b101 %
b101 5
b101 4
b101 F
b101 J
b101 M
b101 P
b101 T
b101 ^
b101 `
b101 b
b101 e
b101 h
b1 0
b1 Y
b101 *
b101 6
b101 ]
b1000 +
b1000 -
b1000 7
b1000 V
0)
#90000
b101 ;
b101 O
b101 d
1)
#100000
0)
#110000
1)
#111000
b1001100010001000100100101011111010100100011001000100000 l
b11 k
b10 j
#120000
1Q
0N
b100 "
b100 2
b100 9
b100 [
b11 .
b11 W
b11 %
b11 5
b11 4
b11 F
b11 J
b11 M
b11 P
b11 T
b11 ^
b11 `
b11 b
b11 e
b11 h
b10 0
b10 Y
b11 *
b11 6
b11 ]
b10000 +
b10000 -
b10000 7
b10000 V
0)
#130000
b11 :
b11 R
b11 g
1)
#140000
0)
#150000
1)
#151000
b1001101010011110101011001011111010100100011001000100000 l
b0 k
b1 m
#160000
1c
b1 !
b1 3
b100 "
b100 2
b1 8
b1 \
b100 9
b100 [
b0 .
b0 W
b1010 %
b1010 5
b1010 4
b1010 F
b1010 J
b1010 M
b1010 P
b1010 T
b1010 ^
b1010 `
b1010 b
b1010 e
b1010 h
b1 /
0=
b1 X
b0 *
b0 6
b0 ]
b10001 +
b10001 -
b10001 7
b10001 V
0)
#170000
b1010 :
b1010 R
b1010 g
1)
#180000
0)
#190000
1)
#191000
b1000001010001000100010001011111010100100011000000100000 l
b1 k
b0 j
b10 m
#200000
0Q
1(
b0 "
b0 2
b1 !
b1 3
1E
b0 9
b0 [
b1 8
b1 \
b1 .
b1 W
b10 /
b0 0
b10 X
b0 Y
b1 *
b1 6
b1 ]
b10 +
b10 -
b10 7
b10 V
0)
#210000
b101 %
b101 5
b101 4
b101 F
b101 J
b101 M
b101 P
b101 T
b101 ^
b101 `
b101 b
b101 e
b101 h
1f
0c
1@
0E
b10 8
b10 \
1$
0(
b10 !
b10 3
b1111 A
b1111 H
b1111 U
b1 Z
b1 1
b1010 D
b1010 G
b1010 S
1)
#220000
0)
#230000
b11001 A
b11001 H
b11001 U
1K
b1111 %
b1111 5
b1111 4
b1111 F
b1111 J
b1111 M
b1111 P
b1111 T
b1111 ^
b1111 `
b1111 b
b1111 e
b1111 h
0f
b1 "
b1 2
1#
0$
b0 !
b0 3
b1 9
b1 [
1>
0@
b0 8
b0 \
b10 1
b10 Z
b1111 ?
b1111 I
b1111 _
1)
#240000
0)
#250000
b11001 A
b11001 H
b11001 U
1c
b1111 %
b1111 5
b1111 4
b1111 F
b1111 J
b1111 M
b1111 P
b1111 T
b1111 ^
b1111 `
b1111 b
b1111 e
b1111 h
0K
1E
b1 8
b1 \
0>
b0 9
b0 [
1(
b1 !
b1 3
0#
b0 "
b0 2
b0 Z
b0 1
b1111 <
b1111 L
b1111 a
1)
#251000
b1010011010101010100001001011111010100100011000000100000 l
b10 k
b11 m
#260000
b1111111111111011 A
b1111111111111011 H
b1111111111111011 U
1&
1(
b1 !
b1 3
1B
1E
b1 8
b1 \
b10 .
b10 W
b11 /
b11 X
b10 *
b10 6
b10 ]
b11 +
b11 -
b11 7
b11 V
0)
#270000
b1010 %
b1010 5
b1010 4
b1010 F
b1010 J
b1010 M
b1010 P
b1010 T
b1010 ^
b1010 `
b1010 b
b1010 e
b1010 h
1i
0c
1$
1&
0(
b100 !
b100 3
1@
1B
0E
b100 8
b100 \
b101 A
b101 H
b101 U
b1 1
b1 Z
b1111 D
b1111 G
b1111 S
1)
#280000
0)
#290000
b1010 A
b1010 H
b1010 U
1K
b101 %
b101 5
b101 4
b101 F
b101 J
b101 M
b101 P
b101 T
b101 ^
b101 `
b101 b
b101 e
b101 h
0i
b1 9
b1 [
1>
1B
0@
b0 8
b0 \
b1 "
b1 2
1#
1&
0$
b0 !
b0 3
b10 Z
b10 1
b101 ?
b101 I
b101 _
1)
#300000
0)
#310000
1c
b1010 A
b1010 H
b1010 U
b101 %
b101 5
b101 4
b101 F
b101 J
b101 M
b101 P
b101 T
b101 ^
b101 `
b101 b
b101 e
b101 h
0K
1(
b1 !
b1 3
1&
0#
b0 "
b0 2
1E
b1 8
b1 \
1B
0>
b0 9
b0 [
b0 1
b0 Z
b101 <
b101 L
b101 a
1)
#311000
b1000001010001000100010001011111010100100011000100100000 l
b1 j
b10 m
#320000
b101 %
b101 5
b101 4
b101 F
b101 J
b101 M
b101 P
b101 T
b101 ^
b101 `
b101 b
b101 e
b101 h
1f
b10100 A
b10100 H
b10100 U
0c
0&
1(
b10 !
b10 3
0B
1E
b10 8
b10 \
b10 /
b1 0
b10 X
b1 Y
b1010 +
b1010 -
b1010 7
b1010 V
0)
#330000
b1010 %
b1010 5
b1010 4
b1010 F
b1010 J
b1010 M
b1010 P
b1010 T
b1010 ^
b1010 `
b1010 b
b1010 e
b1010 h
1i
0f
1@
0E
b100 8
b100 \
1$
0(
b100 !
b100 3
b1111 A
b1111 H
b1111 U
b1 Z
b1 1
b101 D
b101 G
b101 S
1)
#340000
0)
#350000
b10100 A
b10100 H
b10100 U
1N
b1111 %
b1111 5
b1111 4
b1111 F
b1111 J
b1111 M
b1111 P
b1111 T
b1111 ^
b1111 `
b1111 b
b1111 e
b1111 h
0i
b10 "
b10 2
1#
0$
b0 !
b0 3
b10 9
b10 [
1>
0@
b0 8
b0 \
b10 1
b10 Z
b1111 ?
b1111 I
b1111 _
1)
#360000
0)
#370000
b10100 A
b10100 H
b10100 U
1f
b1111 %
b1111 5
b1111 4
b1111 F
b1111 J
b1111 M
b1111 P
b1111 T
b1111 ^
b1111 `
b1111 b
b1111 e
b1111 h
0N
1E
b10 8
b10 \
0>
b0 9
b0 [
1(
b10 !
b10 3
0#
b0 "
b0 2
b0 Z
b0 1
b1111 ;
b1111 O
b1111 d
1)
#371000
b1010011010101010100001001011111010100100011001000100000 l
b1 k
b10 j
b11 m
#380000
b1010 %
b1010 5
b1010 4
b1010 F
b1010 J
b1010 M
b1010 P
b1010 T
b1010 ^
b1010 `
b1010 b
b1010 e
b1010 h
1i
b1111111111111011 A
b1111111111111011 H
b1111111111111011 U
0f
1&
1(
b100 !
b100 3
1B
1E
b100 8
b100 \
b1 .
b1 W
b11 /
b10 0
b11 X
b10 Y
b1 *
b1 6
b1 ]
b10011 +
b10011 -
b10011 7
b10011 V
0)
#390000
b1111 %
b1111 5
b1111 4
b1111 F
b1111 J
b1111 M
b1111 P
b1111 T
b1111 ^
b1111 `
b1111 b
b1111 e
b1111 h
1f
0i
1$
1&
0(
b10 !
b10 3
1@
1B
0E
b10 8
b10 \
b1111111111111011 A
b1111111111111011 H
b1111111111111011 U
b1 1
b1 Z
b1010 D
b1010 G
b1010 S
1)
#400000
0)
#410000
b1111 A
b1111 H
b1111 U
1Q
b1111111111111011 %
b1111111111111011 5
b1111111111111011 4
b1111111111111011 F
b1111111111111011 J
b1111111111111011 M
b1111111111111011 P
b1111111111111011 T
b1111111111111011 ^
b1111111111111011 `
b1111111111111011 b
b1111111111111011 e
b1111111111111011 h
0f
b100 9
b100 [
1>
1B
0@
b0 8
b0 \
b100 "
b100 2
1#
1&
0$
b0 !
b0 3
b10 Z
b10 1
b1111111111111011 ?
b1111111111111011 I
b1111111111111011 _
1)
#420000
0)
#430000
1i
b1111 A
b1111 H
b1111 U
b1111111111111011 %
b1111111111111011 5
b1111111111111011 4
b1111111111111011 F
b1111111111111011 J
b1111111111111011 M
b1111111111111011 P
b1111111111111011 T
b1111111111111011 ^
b1111111111111011 `
b1111111111111011 b
b1111111111111011 e
b1111111111111011 h
0Q
1(
b100 !
b100 3
1&
0#
b0 "
b0 2
1E
b100 8
b100 \
1B
0>
b0 9
b0 [
b0 1
b0 Z
b1111111111111011 :
b1111111111111011 R
b1111111111111011 g
1)
#431000
b1001100010001000100100101011111010100100011000001011010 l
b0 k
b0 j
b0 m
#440000
1K
b1010 A
b1010 H
b1010 U
0i
b1 "
b1 2
0&
0(
b0 !
b0 3
b0 %
b0 5
b0 4
b0 F
b0 J
b0 M
b0 P
b0 T
b0 ^
b0 `
b0 b
b0 e
b0 h
b1 9
b1 [
0B
0E
b0 8
b0 \
b0 .
b0 W
b0 /
b0 0
1=
b0 X
b0 Y
b0 *
b0 6
b0 ]
b0 +
b0 -
b0 7
b0 V
0)
#450000
b0 <
b0 L
b0 a
1)
#460000
0)
#470000
1)
#471000
b100000101000100010001000101111100110000001010110101001000110001 l
b1 k
b10 m
#480000
1c
0K
b1010 A
b1010 H
b1010 U
1(
b1 !
b1 3
b0 "
b0 2
1E
b1 8
b1 \
b0 9
b0 [
b1 .
b1 W
b0 %
b0 5
b0 4
b0 F
b0 J
b0 M
b0 P
b0 T
b0 ^
b0 `
b0 b
b0 e
b0 h
b10 /
0=
b10 X
b1 *
b1 6
b1 ]
b10 +
b10 -
b10 7
b10 V
0)
#490000
b1111 %
b1111 5
b1111 4
b1111 F
b1111 J
b1111 M
b1111 P
b1111 T
b1111 ^
b1111 `
b1111 b
b1111 e
b1111 h
1f
0c
1@
0E
b10 8
b10 \
1$
0(
b10 !
b10 3
b1111 A
b1111 H
b1111 U
b1 Z
b1 1
b0 D
b0 G
b0 S
1)
#500000
0)
#510000
1K
0f
b1 "
b1 2
1#
0$
b0 !
b0 3
b1 9
b1 [
1>
0@
b0 8
b0 \
b10 1
b10 Z
b1111 ?
b1111 I
b1111 _
1)
#520000
0)
#530000
b1111 A
b1111 H
b1111 U
1c
b1111 %
b1111 5
b1111 4
b1111 F
b1111 J
b1111 M
b1111 P
b1111 T
b1111 ^
b1111 `
b1111 b
b1111 e
b1111 h
0K
1E
b1 8
b1 \
0>
b0 9
b0 [
1(
b1 !
b1 3
0#
b0 "
b0 2
b0 Z
b0 1
b1111 <
b1111 L
b1111 a
1)
#531000
b101001101010101010000100101111101010010001100000101001000110000 l
b0 k
b11 m
#540000
b1111111111110001 A
b1111111111110001 H
b1111111111110001 U
1&
1(
b1 !
b1 3
1B
1E
b1 8
b1 \
b0 .
b0 W
b11 /
b11 X
b0 *
b0 6
b0 ]
b11 +
b11 -
b11 7
b11 V
0)
#550000
1$
1&
0(
b1 !
b1 3
1@
1B
0E
b1 8
b1 \
b0 A
b0 H
b0 U
b1 1
b1 Z
b1111 D
b1111 G
b1111 S
1)
#560000
0)
#570000
b1111 A
b1111 H
b1111 U
1K
b0 %
b0 5
b0 4
b0 F
b0 J
b0 M
b0 P
b0 T
b0 ^
b0 `
b0 b
b0 e
b0 h
0c
b1 9
b1 [
1>
1B
0@
b0 8
b0 \
b1 "
b1 2
1#
1&
0$
b0 !
b0 3
b10 Z
b10 1
b0 ?
b0 I
b0 _
1)
#580000
0)
#590000
1c
b1111 A
b1111 H
b1111 U
b0 %
b0 5
b0 4
b0 F
b0 J
b0 M
b0 P
b0 T
b0 ^
b0 `
b0 b
b0 e
b0 h
0K
1(
b1 !
b1 3
1&
0#
b0 "
b0 2
1E
b1 8
b1 \
1B
0>
b0 9
b0 [
b0 1
b0 Z
b0 <
b0 L
b0 a
1)
#600000
0)
#610000
1@
1B
0E
b1 8
b1 \
1$
1&
0(
b1 !
b1 3
b0 A
b0 H
b0 U
b1 Z
b1 1
b0 D
b0 G
b0 S
1)
#620000
0)
#630000
1K
0c
b1 "
b1 2
1#
1&
0$
b0 !
b0 3
b1 9
b1 [
1>
1B
0@
b0 8
b0 \
b10 1
b10 Z
1)
#640000
0)
#650000
1c
b0 A
b0 H
b0 U
b0 %
b0 5
b0 4
b0 F
b0 J
b0 M
b0 P
b0 T
b0 ^
b0 `
b0 b
b0 e
b0 h
0K
1E
b1 8
b1 \
1B
0>
b0 9
b0 [
1(
b1 !
b1 3
1&
0#
b0 "
b0 2
b0 Z
b0 1
1)
#660000
0)
#670000
1$
1&
0(
b1 !
b1 3
1@
1B
0E
b1 8
b1 \
b1 1
b1 Z
1)
